README.rst
setup.cfg
setup.py
wxpay/__init__.py
wxpay/exceptions.py
wxpay.egg-info/PKG-INFO
wxpay.egg-info/SOURCES.txt
wxpay.egg-info/dependency_links.txt
wxpay.egg-info/requires.txt
wxpay.egg-info/top_level.txt