Metadata-Version: 1.0
Name: wxpay
Version: 0.13
Summary: a lib for wechat payment
Home-page: https://github.com/SIvaCoHan/wxpay
Author: sivacohan
Author-email: sivacohan@gmail.com
License: UNKNOWN
Keywords: wechat,payment,library
Platform: UNKNOWN
